{"106":{"id":"106","name":"Japan Founders PR Index","code":"JFIP","investmentammount":"257768.2321300810","divpvalue":"","indexvalue":"2074.3791660","divisor":"","type":"1","cash_adjust":"0","curr":"JPY","status":"1","dateAdded":"2014-09-25 02:18:21","lastupdated":"2014-09-26 02:32:11","dateStart":"2014-10-01","usersignoff":"1","dbusersignoff":"1","submitted":"1","finalsignoff":"1","runindex":"1","addtype":"0","zone":"2","calcdate":"0000-00-00","rebalance":"0","client_id":"1","display_currency":"1","ireturn":"1","ica":"0","recalc":"0","div_type":"1","currency_hedged":"0","priority":"0","client":"horizon","index_value":{"id":"7564","dateAdded":"2014-12-09 17:43:33","indxx_id":"106","code":"JFIP","market_value":"259602.721631","indxx_value":"2087.11","date":"2014-12-09","olddivisor":"124.383959798","newdivisor":"124.383959798","divisor_impact":0},"values":[{"id":"4966","name":"Ariake Japan Co Ltd","isin":"JP3125800007","ticker":"2815 JP Equity","curr":"JPY","divcurr":"JPY","sedol":"6049632","cusip":"","countryname":"Japan","calcprice":"2863","localprice":"2863","currencyfactor":"1","calcshare":"0.68977316598897500","ca":null,"newcalcprice":2863,"newlocalprice":2863,"newcalcshare":"0.68977316598897500"},{"id":"4967","name":"Universal Entertainment Corp","isin":"JP3126130008","ticker":"6425 JP Equity","curr":"JPY","divcurr":"JPY","sedol":"6126892","cusip":"","countryname":"Japan","calcprice":"1836","localprice":"1836","currencyfactor":"1","calcshare":"0.96867477426149200","ca":null,"newcalcprice":1836,"newlocalprice":1836,"newcalcshare":"0.96867477426149200"},{"id":"4968","name":"Alpen Co Ltd","isin":"JP3126470008","ticker":"3028 JP Equity","curr":"JPY","divcurr":"JPY","sedol":"B0ZGMK6","cusip":"","countryname":"Japan","calcprice":"1762","localprice":"1762","currencyfactor":"1","calcshare":"1.01792942380021000","ca":null,"newcalcprice":1762,"newlocalprice":1762,"newcalcshare":"1.01792942380021000"},{"id":"4969","name":"Izumi Co Ltd","isin":"JP3138400001","ticker":"8273 JP Equity","curr":"JPY","divcurr":"JPY","sedol":"6468152","cusip":"","countryname":"Japan","calcprice":"3835","localprice":"3835","currencyfactor":"1","calcshare":"0.47521889334847600","ca":null,"newcalcprice":3835,"newlocalprice":3835,"newcalcshare":"0.47521889334847600"},{"id":"4970","name":"J Trust Co Ltd","isin":"JP3142350002","ticker":"8508 JP Equity","curr":"JPY","divcurr":"JPY","sedol":"6126717","cusip":"","countryname":"Japan","calcprice":"1073","localprice":"1073","currencyfactor":"1","calcshare":"1.54267249257942000","ca":null,"newcalcprice":1073,"newlocalprice":1073,"newcalcshare":"1.54267249257942000"},{"id":"4971","name":"Ito En Ltd","isin":"JP3143000002","ticker":"2593 JP Equity","curr":"JPY","divcurr":"JPY","sedol":"6455789","cusip":"","countryname":"Japan","calcprice":"2137","localprice":"2137","currencyfactor":"1","calcshare":"0.74975344129236400","ca":null,"newcalcprice":2137,"newlocalprice":2137,"newcalcshare":"0.74975344129236400"},{"id":"4972","name":"Iriso Electronics Co Ltd","isin":"JP3149800009","ticker":"6908 JP Equity","curr":"JPY","divcurr":"JPY","sedol":"6461128","cusip":"","countryname":"Japan","calcprice":"6340","localprice":"6340","currencyfactor":"1","calcshare":"0.21689629441122800","ca":null,"newcalcprice":6340,"newlocalprice":6340,"newcalcshare":"0.21689629441122800"},{"id":"4973","name":"GMO internet Inc","isin":"JP3152750000","ticker":"9449 JP Equity","curr":"JPY","divcurr":"JPY","sedol":"6170167","cusip":"","countryname":"Japan","calcprice":"1040","localprice":"1040","currencyfactor":"1","calcshare":"1.75926994355774000","ca":null,"newcalcprice":1040,"newlocalprice":1040,"newcalcshare":"1.75926994355774000"},{"id":"4974","name":"Internet Initiative Japan Inc","isin":"JP3152820001","ticker":"3774 JP Equity","curr":"JPY","divcurr":"JPY","sedol":"B05H328","cusip":"","countryname":"Japan","calcprice":"2492","localprice":"2492","currencyfactor":"1","calcshare":"0.78348054166539000","ca":null,"newcalcprice":2492,"newlocalprice":2492,"newcalcshare":"0.78348054166539000"},{"id":"4975","name":"Infomart Corp","isin":"JP3153480003","ticker":"2492 JP Equity","curr":"JPY","divcurr":"JPY","sedol":"B18RC03","cusip":"","countryname":"Japan","calcprice":"2158","localprice":"2158","currencyfactor":"1","calcshare":"0.94604956226081600","ca":null,"newcalcprice":2158,"newlocalprice":2158,"newcalcshare":"0.94604956226081600"},{"id":"4976","name":"Wellnet Corp","isin":"JP3155370004","ticker":"2428 JP Equity","curr":"JPY","divcurr":"JPY","sedol":"B045FZ0","cusip":"","countryname":"Japan","calcprice":"1890","localprice":"1890","currencyfactor":"1","calcshare":"1.00558732339617000","ca":null,"newcalcprice":1890,"newlocalprice":1890,"newcalcshare":"1.00558732339617000"},{"id":"4977","name":"Ushio Inc","isin":"JP3156400008","ticker":"6925 JP Equity","curr":"JPY","divcurr":"JPY","sedol":"6918981","cusip":"","countryname":"Japan","calcprice":"1291","localprice":"1291","currencyfactor":"1","calcshare":"1.42061765425951000","ca":null,"newcalcprice":1291,"newlocalprice":1291,"newcalcshare":"1.42061765425951000"},{"id":"4978","name":"HIS Co Ltd","isin":"JP3160740001","ticker":"9603 JP Equity","curr":"JPY","divcurr":"JPY","sedol":"6400433","cusip":"","countryname":"Japan","calcprice":"3220","localprice":"3220","currencyfactor":"1","calcshare":"0.59789812705875800","ca":null,"newcalcprice":3220,"newlocalprice":3220,"newcalcshare":"0.59789812705875800"},{"id":"4979","name":"Avex Group Holdings Inc","isin":"JP3160950006","ticker":"7860 JP Equity","curr":"JPY","divcurr":"JPY","sedol":"6129073","cusip":"","countryname":"Japan","calcprice":"1761","localprice":"1761","currencyfactor":"1","calcshare":"1.00674985209374000","ca":null,"newcalcprice":1761,"newlocalprice":1761,"newcalcshare":"1.00674985209374000"},{"id":"4980","name":"SMS Co Ltd","isin":"JP3162350007","ticker":"2175 JP Equity","curr":"JPY","divcurr":"JPY","sedol":"B2PLYM1","cusip":"","countryname":"Japan","calcprice":"2656","localprice":"2656","currencyfactor":"1","calcshare":"0.61652291827333200","ca":null,"newcalcprice":2656,"newlocalprice":2656,"newcalcshare":"0.61652291827333200"},{"id":"4981","name":"Square Enix Holdings Co Ltd","isin":"JP3164630000","ticker":"9684 JP Equity","curr":"JPY","divcurr":"JPY","sedol":"6309262","cusip":"","countryname":"Japan","calcprice":"2395","localprice":"2395","currencyfactor":"1","calcshare":"0.75007633252461800","ca":null,"newcalcprice":2395,"newlocalprice":2395,"newcalcshare":"0.75007633252461800"},{"id":"4982","name":"FP Corp","isin":"JP3167000003","ticker":"7947 JP Equity","curr":"JPY","divcurr":"JPY","sedol":"6329947","cusip":"","countryname":"Japan","calcprice":"3675","localprice":"3675","currencyfactor":"1","calcshare":"0.55116368484878600","ca":null,"newcalcprice":3675,"newlocalprice":3675,"newcalcshare":"0.55116368484878600"},{"id":"4983","name":"MCJ Co Ltd","isin":"JP3167420003","ticker":"6670 JP Equity","curr":"JPY","divcurr":"JPY","sedol":"B00TL47","cusip":"","countryname":"Japan","calcprice":"606","localprice":"606","currencyfactor":"1","calcshare":"4.85146864657984000","ca":null,"newcalcprice":606,"newlocalprice":606,"newcalcshare":"4.85146864657984000"},{"id":"4984","name":"MTI Ltd","isin":"JP3167480007","ticker":"9438 JP Equity","curr":"JPY","divcurr":"JPY","sedol":"6201948","cusip":"","countryname":"Japan","calcprice":"876","localprice":"876","currencyfactor":"1","calcshare":"1.75395492862252000","ca":null,"newcalcprice":876,"newlocalprice":876,"newcalcshare":"1.75395492862252000"},{"id":"4985","name":"Arealink Co Ltd","isin":"JP3167620008","ticker":"8914 JP Equity","curr":"JPY","divcurr":"JPY","sedol":"6654092","cusip":"","countryname":"Japan","calcprice":"144","localprice":"144","currencyfactor":"1","calcshare":"12.53005211598680000","ca":null,"newcalcprice":144,"newlocalprice":144,"newcalcshare":"12.53005211598680000"},{"id":"4986","name":"Elecom Co Ltd","isin":"JP3168200008","ticker":"6750 JP Equity","curr":"JPY","divcurr":"JPY","sedol":"6388528","cusip":"","countryname":"Japan","calcprice":"2479","localprice":"2479","currencyfactor":"1","calcshare":"0.69224055807717100","ca":null,"newcalcprice":2479,"newlocalprice":2479,"newcalcshare":"0.69224055807717100"},{"id":"4987","name":"en-japan Inc","isin":"JP3168700007","ticker":"4849 JP Equity","curr":"JPY","divcurr":"JPY","sedol":"6352750","cusip":"","countryname":"Japan","calcprice":"1705","localprice":"1705","currencyfactor":"1","calcshare":"0.78032134593286900","ca":null,"newcalcprice":1705,"newlocalprice":1705,"newcalcshare":"0.78032134593286900"},{"id":"4988","name":"Endo Lighting Corp","isin":"JP3169600008","ticker":"6932 JP Equity","curr":"JPY","divcurr":"JPY","sedol":"6308559","cusip":"","countryname":"Japan","calcprice":"1352","localprice":"1352","currencyfactor":"1","calcshare":"1.19785229994647000","ca":null,"newcalcprice":1352,"newlocalprice":1352,"newcalcshare":"1.19785229994647000"},{"id":"4989","name":"Oizumi Corp","isin":"JP3170100006","ticker":"6428 JP Equity","curr":"JPY","divcurr":"JPY","sedol":"6289773","cusip":"","countryname":"Japan","calcprice":"888","localprice":"888","currencyfactor":"1","calcshare":"1.56204237141001000","ca":null,"newcalcprice":888,"newlocalprice":888,"newcalcshare":"1.56204237141001000"},{"id":"4990","name":"OPT Inc","isin":"JP3197730009","ticker":"2389 JP Equity","curr":"JPY","divcurr":"JPY","sedol":"6731393","cusip":"","countryname":"Japan","calcprice":"791","localprice":"791","currencyfactor":"1","calcshare":"2.26780891161740000","ca":null,"newcalcprice":791,"newlocalprice":791,"newcalcshare":"2.26780891161740000"},{"id":"4991","name":"Kakaku.com Inc","isin":"JP3206000006","ticker":"2371 JP Equity","curr":"JPY","divcurr":"JPY","sedol":"6689533","cusip":"","countryname":"Japan","calcprice":"1872","localprice":"1872","currencyfactor":"1","calcshare":"1.04105035512383000","ca":null,"newcalcprice":1872,"newlocalprice":1872,"newcalcshare":"1.04105035512383000"},{"id":"4992","name":"Capcom Co Ltd","isin":"JP3218900003","ticker":"9697 JP Equity","curr":"JPY","divcurr":"JPY","sedol":"6173694","cusip":"","countryname":"Japan","calcprice":"1761","localprice":"1761","currencyfactor":"1","calcshare":"0.99015192957485100","ca":null,"newcalcprice":1761,"newlocalprice":1761,"newcalcshare":"0.99015192957485100"},{"id":"4993","name":"GungHo Online Entertainment Inc","isin":"JP3235900002","ticker":"3765 JP Equity","curr":"JPY","divcurr":"JPY","sedol":"B064D84","cusip":"","countryname":"Japan","calcprice":"528","localprice":"528","currencyfactor":"1","calcshare":"3.23731829762484000","ca":null,"newcalcprice":528,"newlocalprice":528,"newcalcshare":"3.23731829762484000"},{"id":"4994","name":"Keyence Corp","isin":"JP3236200006","ticker":"6861 JP Equity","curr":"JPY","divcurr":"JPY","sedol":"6490995","cusip":"","countryname":"Japan","calcprice":"55310","localprice":"55310","currencyfactor":"1","calcshare":"0.03621327048803750","ca":null,"newcalcprice":55310,"newlocalprice":55310,"newcalcshare":"0.03621327048803750"},{"id":"4995","name":"COOKPAD Inc","isin":"JP3266170004","ticker":"2193 JP Equity","curr":"JPY","divcurr":"JPY","sedol":"B5MTK10","cusip":"","countryname":"Japan","calcprice":"3700","localprice":"3700","currencyfactor":"1","calcshare":"0.48514686465798400","ca":null,"newcalcprice":3700,"newlocalprice":3700,"newcalcshare":"0.48514686465798400"},{"id":"4996","name":"Kura Corp","isin":"JP3268200007","ticker":"2695 JP Equity","curr":"JPY","divcurr":"JPY","sedol":"6345965","cusip":"","countryname":"Japan","calcprice":"2966","localprice":"2966","currencyfactor":"1","calcshare":"0.57010711755226300","ca":null,"newcalcprice":2966,"newlocalprice":2966,"newcalcshare":"0.57010711755226300"},{"id":"4997","name":"Create Restaurants Holdings Inc","isin":"JP3269930008","ticker":"3387 JP Equity","curr":"JPY","divcurr":"JPY","sedol":"B0J2LC5","cusip":"","countryname":"Japan","calcprice":"1567","localprice":"1567","currencyfactor":"1","calcshare":"1.34492451283565000","ca":null,"newcalcprice":1567,"newlocalprice":1567,"newcalcshare":"1.34492451283565000"},{"id":"4998","name":"Gree Inc","isin":"JP3274070006","ticker":"3632 JP Equity","curr":"JPY","divcurr":"JPY","sedol":"B3FJNX6","cusip":"","countryname":"Japan","calcprice":"758","localprice":"758","currencyfactor":"1","calcshare":"2.27670227989825000","ca":null,"newcalcprice":758,"newlocalprice":758,"newcalcshare":"2.27670227989825000"},{"id":"4999","name":"Gurunavi Inc","isin":"JP3274180003","ticker":"2440 JP Equity","curr":"JPY","divcurr":"JPY","sedol":"B06WPV5","cusip":"","countryname":"Japan","calcprice":"1685","localprice":"1685","currencyfactor":"1","calcshare":"1.12438814985291000","ca":null,"newcalcprice":1685,"newlocalprice":1685,"newcalcshare":"1.12438814985291000"},{"id":"5000","name":"Koei Tecmo Holdings Co Ltd","isin":"JP3283460008","ticker":"3635 JP Equity","curr":"JPY","divcurr":"JPY","sedol":"B60DR09","cusip":"","countryname":"Japan","calcprice":"1753","localprice":"1753","currencyfactor":"1","calcshare":"0.99184353309918100","ca":null,"newcalcprice":1753,"newlocalprice":1753,"newcalcshare":"0.99184353309918100"},{"id":"5001","name":"Kohnan Shoji Co Ltd","isin":"JP3283750002","ticker":"7516 JP Equity","curr":"JPY","divcurr":"JPY","sedol":"6504379","cusip":"","countryname":"Japan","calcprice":"1345","localprice":"1345","currencyfactor":"1","calcshare":"1.42760429846079000","ca":null,"newcalcprice":1345,"newlocalprice":1345,"newcalcshare":"1.42760429846079000"},{"id":"5002","name":"Cosmos Pharmaceutical Corp","isin":"JP3298400007","ticker":"3349 JP Equity","curr":"JPY","divcurr":"JPY","sedol":"B036QP1","cusip":"","countryname":"Japan","calcprice":"15980","localprice":"15980","currencyfactor":"1","calcshare":"0.12648345999434700","ca":null,"newcalcprice":15980,"newlocalprice":15980,"newcalcshare":"0.12648345999434700"},{"id":"5003","name":"Konami Corp","isin":"JP3300200007","ticker":"9766 JP Equity","curr":"JPY","divcurr":"JPY","sedol":"6496681","cusip":"","countryname":"Japan","calcprice":"2216","localprice":"2216","currencyfactor":"1","calcshare":"0.76759684624158800","ca":null,"newcalcprice":2216,"newlocalprice":2216,"newcalcshare":"0.76759684624158800"},{"id":"5004","name":"Goldcrest Co Ltd","isin":"JP3306800008","ticker":"8871 JP Equity","curr":"JPY","divcurr":"JPY","sedol":"6123343","cusip":"","countryname":"Japan","calcprice":"2143","localprice":"2143","currencyfactor":"1","calcshare":"0.84383587409019500","ca":null,"newcalcprice":2143,"newlocalprice":2143,"newcalcshare":"0.84383587409019500"},{"id":"5005","name":"Saizeriya Co Ltd","isin":"JP3310500008","ticker":"7581 JP Equity","curr":"JPY","divcurr":"JPY","sedol":"6111779","cusip":"","countryname":"Japan","calcprice":"1589","localprice":"1589","currencyfactor":"1","calcshare":"1.15419300471979000","ca":null,"newcalcprice":1589,"newlocalprice":1589,"newcalcshare":"1.15419300471979000"},{"id":"5006","name":"Sanix Inc","isin":"JP3322600002","ticker":"4651 JP Equity","curr":"JPY","divcurr":"JPY","sedol":"6853015","cusip":"","countryname":"Japan","calcprice":"520","localprice":"520","currencyfactor":"1","calcshare":"1.93304910557399000","ca":null,"newcalcprice":520,"newlocalprice":520,"newcalcshare":"1.93304910557399000"},{"id":"5007","name":"Sankyo Co Ltd","isin":"JP3326410002","ticker":"6417 JP Equity","curr":"JPY","divcurr":"JPY","sedol":"6775432","cusip":"","countryname":"Japan","calcprice":"4015","localprice":"4015","currencyfactor":"1","calcshare":"0.42740545868028500","ca":null,"newcalcprice":4015,"newlocalprice":4015,"newcalcshare":"0.42740545868028500"},{"id":"5008","name":"Sangetsu Co Ltd","isin":"JP3330000005","ticker":"8130 JP Equity","curr":"JPY","divcurr":"JPY","sedol":"6774655","cusip":"","countryname":"Japan","calcprice":"2886","localprice":"2886","currencyfactor":"1","calcshare":"0.61959346998298200","ca":null,"newcalcprice":2886,"newlocalprice":2886,"newcalcshare":"0.61959346998298200"},{"id":"5009","name":"Sun Frontier Fudousan Co Ltd","isin":"JP3336950005","ticker":"8934 JP Equity","curr":"JPY","divcurr":"JPY","sedol":"B03BJB3","cusip":"","countryname":"Japan","calcprice":"1141","localprice":"1141","currencyfactor":"1","calcshare":"1.45869115923129000","ca":null,"newcalcprice":1141,"newlocalprice":1141,"newcalcshare":"1.45869115923129000"},{"id":"5010","name":"St Marc Holdings Co Ltd","isin":"JP3337070001","ticker":"3395 JP Equity","curr":"JPY","divcurr":"JPY","sedol":"B0SQYV8","cusip":"","countryname":"Japan","calcprice":"6770","localprice":"6770","currencyfactor":"1","calcshare":"0.28412353085190300","ca":null,"newcalcprice":6770,"newlocalprice":6770,"newcalcshare":"0.28412353085190300"},{"id":"5011","name":"Sanrio Co Ltd","isin":"JP3343200006","ticker":"8136 JP Equity","curr":"JPY","divcurr":"JPY","sedol":"6776349","cusip":"","countryname":"Japan","calcprice":"3280","localprice":"3280","currencyfactor":"1","calcshare":"0.50483398380352500","ca":null,"newcalcprice":3280,"newlocalprice":3280,"newcalcshare":"0.50483398380352500"},{"id":"5012","name":"Shima Seiki Manufacturing Ltd","isin":"JP3356500003","ticker":"6222 JP Equity","curr":"JPY","divcurr":"JPY","sedol":"6806008","cusip":"","countryname":"Japan","calcprice":"2185","localprice":"2185","currencyfactor":"1","calcshare":"0.94297630975753300","ca":null,"newcalcprice":2185,"newlocalprice":2185,"newcalcshare":"0.94297630975753300"},{"id":"5013","name":"SHO-BOND Holdings Co Ltd","isin":"JP3360250009","ticker":"1414 JP Equity","curr":"JPY","divcurr":"JPY","sedol":"B29T1W0","cusip":"","countryname":"Japan","calcprice":"4500","localprice":"4500","currencyfactor":"1","calcshare":"0.40457078841397500","ca":null,"newcalcprice":4500,"newlocalprice":4500,"newcalcshare":"0.40457078841397500"},{"id":"5014","name":"Jin Co Ltd","isin":"JP3386110005","ticker":"3046 JP Equity","curr":"JPY","divcurr":"JPY","sedol":"B18D6G5","cusip":"","countryname":"Japan","calcprice":"2843","localprice":"2843","currencyfactor":"1","calcshare":"0.57292014609281700","ca":null,"newcalcprice":2843,"newlocalprice":2843,"newcalcshare":"0.57292014609281700"},{"id":"5015","name":"JP-Holdings Inc\/Japan","isin":"JP3386190007","ticker":"2749 JP Equity","curr":"JPY","divcurr":"JPY","sedol":"6545936","cusip":"","countryname":"Japan","calcprice":"376","localprice":"376","currencyfactor":"1","calcshare":"4.13700057986262000","ca":null,"newcalcprice":376,"newlocalprice":376,"newcalcshare":"4.13700057986262000"},{"id":"5016","name":"GCA Savvian Corp","isin":"JP3386390003","ticker":"2174 JP Equity","curr":"JPY","divcurr":"JPY","sedol":"B2PG341","cusip":"","countryname":"Japan","calcprice":"1196","localprice":"1196","currencyfactor":"1","calcshare":"1.78450537307599000","ca":null,"newcalcprice":1196,"newlocalprice":1196,"newcalcshare":"1.78450537307599000"},{"id":"5017","name":"Sugi Holdings Co Ltd","isin":"JP3397060009","ticker":"7649 JP Equity","curr":"JPY","divcurr":"JPY","sedol":"6259011","cusip":"","countryname":"Japan","calcprice":"4905","localprice":"4905","currencyfactor":"1","calcshare":"0.37862548785264400","ca":null,"newcalcprice":4905,"newlocalprice":4905,"newcalcshare":"0.37862548785264400"},{"id":"5018","name":"Start Today Co Ltd","isin":"JP3399310006","ticker":"3092 JP Equity","curr":"JPY","divcurr":"JPY","sedol":"B292RC1","cusip":"","countryname":"Japan","calcprice":"2353","localprice":"2353","currencyfactor":"1","calcshare":"0.73087588926653900","ca":null,"newcalcprice":2353,"newlocalprice":2353,"newcalcshare":"0.73087588926653900"},{"id":"5019","name":"Sparx Group Co Ltd","isin":"JP3399900004","ticker":"8739 JP Equity","curr":"JPY","divcurr":"JPY","sedol":"6419224","cusip":"","countryname":"Japan","calcprice":"223","localprice":"223","currencyfactor":"1","calcshare":"7.81021185705006000","ca":null,"newcalcprice":223,"newlocalprice":223,"newcalcshare":"7.81021185705006000"},{"id":"5020","name":"Zuiko Corp","isin":"JP3411900008","ticker":"6279 JP Equity","curr":"JPY","divcurr":"JPY","sedol":"6989590","cusip":"","countryname":"Japan","calcprice":"5680","localprice":"5680","currencyfactor":"1","calcshare":"0.32433468233187400","ca":null,"newcalcprice":5680,"newlocalprice":5680,"newcalcshare":"0.32433468233187400"},{"id":"5021","name":"Sega Sammy Holdings Inc","isin":"JP3419050004","ticker":"6460 JP Equity","curr":"JPY","divcurr":"JPY","sedol":"B02RK08","cusip":"","countryname":"Japan","calcprice":"1610","localprice":"1610","currencyfactor":"1","calcshare":"0.98067412394265900","ca":null,"newcalcprice":1610,"newlocalprice":1610,"newcalcshare":"0.98067412394265900"},{"id":"5022","name":"Secom Co Ltd","isin":"JP3421800008","ticker":"9735 JP Equity","curr":"JPY","divcurr":"JPY","sedol":"6791591","cusip":"","countryname":"Japan","calcprice":"7024","localprice":"7024","currencyfactor":"1","calcshare":"0.26361090421101300","ca":null,"newcalcprice":7024,"newlocalprice":7024,"newcalcshare":"0.26361090421101300"},{"id":"5023","name":"Seria Co Ltd","isin":"JP3423520000","ticker":"2782 JP Equity","curr":"JPY","divcurr":"JPY","sedol":"6680718","cusip":"","countryname":"Japan","calcprice":"3920","localprice":"3920","currencyfactor":"1","calcshare":"0.42428191087019800","ca":null,"newcalcprice":3920,"newlocalprice":3920,"newcalcshare":"0.42428191087019800"},{"id":"5024","name":"Zensho Holdings Co Ltd","isin":"JP3429300001","ticker":"7550 JP Equity","curr":"JPY","divcurr":"JPY","sedol":"6042608","cusip":"","countryname":"Japan","calcprice":"965","localprice":"965","currencyfactor":"1","calcshare":"1.68277994601175000","ca":null,"newcalcprice":965,"newlocalprice":965,"newcalcshare":"1.68277994601175000"},{"id":"5025","name":"Arcland Sakamoto Co Ltd","isin":"JP3100100001","ticker":"9842 JP Equity","curr":"JPY","divcurr":"JPY","sedol":"6048004","cusip":"","countryname":"Japan","calcprice":"2507","localprice":"2507","currencyfactor":"1","calcshare":"0.67376295710722000","ca":null,"newcalcprice":2507,"newlocalprice":2507,"newcalcshare":"0.67376295710722000"},{"id":"5026","name":"Aiful Corp","isin":"JP3105040004","ticker":"8515 JP Equity","curr":"JPY","divcurr":"JPY","sedol":"6019419","cusip":"","countryname":"Japan","calcprice":"426","localprice":"426","currencyfactor":"1","calcshare":"3.79450379983042000","ca":null,"newcalcprice":426,"newlocalprice":426,"newcalcshare":"3.79450379983042000"},{"id":"5027","name":"Ai Holdings Corp","isin":"JP3105090009","ticker":"3076 JP Equity","curr":"JPY","divcurr":"JPY","sedol":"B1TK201","cusip":"","countryname":"Japan","calcprice":"2280","localprice":"2280","currencyfactor":"1","calcshare":"0.79239183081081100","ca":null,"newcalcprice":2280,"newlocalprice":2280,"newcalcshare":"0.79239183081081100"},{"id":"5028","name":"I'll Inc","isin":"JP3105180008","ticker":"3854 JP Equity","curr":"JPY","divcurr":"JPY","sedol":"B1Y8Y93","cusip":"","countryname":"Japan","calcprice":"1929","localprice":"1929","currencyfactor":"1","calcshare":"0.74590031868186800","ca":null,"newcalcprice":1929,"newlocalprice":1929,"newcalcshare":"0.74590031868186800"},{"id":"5029","name":"Outsourcing Inc","isin":"JP3105270007","ticker":"2427 JP Equity","curr":"JPY","divcurr":"JPY","sedol":"B03XKH2","cusip":"","countryname":"Japan","calcprice":"1670","localprice":"1670","currencyfactor":"1","calcshare":"1.07577346764803000","ca":null,"newcalcprice":1670,"newlocalprice":1670,"newcalcshare":"1.07577346764803000"},{"id":"5030","name":"AOKI Holdings Inc","isin":"JP3105400000","ticker":"8214 JP Equity","curr":"JPY","divcurr":"JPY","sedol":"6045759","cusip":"","countryname":"Japan","calcprice":"1185","localprice":"1185","currencyfactor":"1","calcshare":"1.32952461383371000","ca":null,"newcalcprice":1185,"newlocalprice":1185,"newcalcshare":"1.32952461383371000"},{"id":"5031","name":"Asahi Intecc Co Ltd","isin":"JP3110650003","ticker":"7747 JP Equity","curr":"JPY","divcurr":"JPY","sedol":"B019MQ5","cusip":"","countryname":"Japan","calcprice":"5900","localprice":"5900","currencyfactor":"1","calcshare":"0.34833544882443300","ca":null,"newcalcprice":5900,"newlocalprice":5900,"newcalcshare":"0.34833544882443300"},{"id":"5032","name":"Asukanet Co Ltd","isin":"JP3119670002","ticker":"2438 JP Equity","curr":"JPY","divcurr":"JPY","sedol":"B06JW37","cusip":"","countryname":"Japan","calcprice":"2629","localprice":"2629","currencyfactor":"1","calcshare":"0.4129643732358","ca":null,"newcalcprice":2629,"newlocalprice":2629,"newcalcshare":"0.4129643732358"},{"id":"5033","name":"Aderans Co Ltd","isin":"JP3121600005","ticker":"8170 JP Equity","curr":"JPY","divcurr":"JPY","sedol":"6007395","cusip":"","countryname":"Japan","calcprice":"1249","localprice":"1249","currencyfactor":"1","calcshare":"1.26208495950881000","ca":null,"newcalcprice":1249,"newlocalprice":1249,"newcalcshare":"1.26208495950881000"},{"id":"5034","name":"Advantage Risk Management Co Ltd","isin":"JP3122410008","ticker":"8769 JP Equity","curr":"JPY","divcurr":"JPY","sedol":"B1H58V1","cusip":"","countryname":"Japan","calcprice":"988","localprice":"988","currencyfactor":"1","calcshare":"1.64309173973789000","ca":null,"newcalcprice":988,"newlocalprice":988,"newcalcshare":"1.64309173973789000"},{"id":"5035","name":"M3 Inc","isin":"JP3435750009","ticker":"2413 JP Equity","curr":"JPY","divcurr":"JPY","sedol":"B02K2M3","cusip":"","countryname":"Japan","calcprice":"1979","localprice":"1979","currencyfactor":"1","calcshare":"0.98288783528338800","ca":null,"newcalcprice":1979,"newlocalprice":1979,"newcalcshare":"0.98288783528338800"},{"id":"5036","name":"SoftBank Corp","isin":"JP3436100006","ticker":"9984 JP Equity","curr":"JPY","divcurr":"JPY","sedol":"6770620","cusip":"","countryname":"Japan","calcprice":"7501","localprice":"7501","currencyfactor":"1","calcshare":"0.21877618943878400","ca":null,"newcalcprice":7501,"newlocalprice":7501,"newcalcshare":"0.21877618943878400"},{"id":"5037","name":"SBI Holdings Inc\/Japan","isin":"JP3436120004","ticker":"8473 JP Equity","curr":"JPY","divcurr":"JPY","sedol":"6309466","cusip":"","countryname":"Japan","calcprice":"1412","localprice":"1412","currencyfactor":"1","calcshare":"1.36495081827756000","ca":null,"newcalcprice":1412,"newlocalprice":1412,"newcalcshare":"1.36495081827756000"},{"id":"5038","name":"Takeuchi Manufacturing Co Ltd","isin":"JP3462660006","ticker":"6432 JP Equity","curr":"JPY","divcurr":"JPY","sedol":"6565031","cusip":"","countryname":"Japan","calcprice":"4930","localprice":"4930","currencyfactor":"1","calcshare":"0.34217627585897100","ca":null,"newcalcprice":4930,"newlocalprice":4930,"newcalcshare":"0.34217627585897100"},{"id":"5039","name":"Daiichikosho Co Ltd","isin":"JP3475200006","ticker":"7458 JP Equity","curr":"JPY","divcurr":"JPY","sedol":"6253132","cusip":"","countryname":"Japan","calcprice":"3220","localprice":"3220","currencyfactor":"1","calcshare":"0.58211137838307600","ca":null,"newcalcprice":3220,"newlocalprice":3220,"newcalcshare":"0.58211137838307600"},{"id":"5040","name":"Dydo Drinco Inc","isin":"JP3488400007","ticker":"2590 JP Equity","curr":"JPY","divcurr":"JPY","sedol":"6374992","cusip":"","countryname":"Japan","calcprice":"5010","localprice":"5010","currencyfactor":"1","calcshare":"0.39583573730049100","ca":null,"newcalcprice":5010,"newlocalprice":5010,"newcalcshare":"0.39583573730049100"},{"id":"5041","name":"Take And Give Needs Co Ltd","isin":"JP3539350003","ticker":"4331 JP Equity","curr":"JPY","divcurr":"JPY","sedol":"6421519","cusip":"","countryname":"Japan","calcprice":"1035","localprice":"1035","currencyfactor":"1","calcshare":"1.45382073799847000","ca":null,"newcalcprice":1035,"newlocalprice":1035,"newcalcshare":"1.45382073799847000"},{"id":"5042","name":"tella Inc","isin":"JP3545900007","ticker":"2191 JP Equity","curr":"JPY","divcurr":"JPY","sedol":"B5BVHQ1","cusip":"","countryname":"Japan","calcprice":"1485","localprice":"1485","currencyfactor":"1","calcshare":"1.10302548709447000","ca":null,"newcalcprice":1485,"newlocalprice":1485,"newcalcshare":"1.10302548709447000"},{"id":"5043","name":"Dip Corp","isin":"JP3548640006","ticker":"2379 JP Equity","curr":"JPY","divcurr":"JPY","sedol":"6714071","cusip":"","countryname":"Japan","calcprice":"4160","localprice":"4160","currencyfactor":"1","calcshare":"0.35617121556690400","ca":null,"newcalcprice":4160,"newlocalprice":4160,"newcalcshare":"0.35617121556690400"},{"id":"5044","name":"Token Corp","isin":"JP3590900001","ticker":"1766 JP Equity","curr":"JPY","divcurr":"JPY","sedol":"6898447","cusip":"","countryname":"Japan","calcprice":"5100","localprice":"5100","currencyfactor":"1","calcshare":"0.35399943986222800","ca":null,"newcalcprice":5100,"newlocalprice":5100,"newcalcshare":"0.35399943986222800"},{"id":"5045","name":"Trancom Co Ltd","isin":"JP3635650009","ticker":"9058 JP Equity","curr":"JPY","divcurr":"JPY","sedol":"6890034","cusip":"","countryname":"Japan","calcprice":"4870","localprice":"4870","currencyfactor":"1","calcshare":"0.36022280126621800","ca":null,"newcalcprice":4870,"newlocalprice":4870,"newcalcshare":"0.36022280126621800"},{"id":"5046","name":"Transcosmos Inc","isin":"JP3635700002","ticker":"9715 JP Equity","curr":"JPY","divcurr":"JPY","sedol":"6900955","cusip":"","countryname":"Japan","calcprice":"2031","localprice":"2031","currencyfactor":"1","calcshare":"0.81692178429745000","ca":null,"newcalcprice":2031,"newlocalprice":2031,"newcalcshare":"0.81692178429745000"},{"id":"5047","name":"Toridoll.corp","isin":"JP3636650008","ticker":"3397 JP Equity","curr":"JPY","divcurr":"JPY","sedol":"B0WHPP8","cusip":"","countryname":"Japan","calcprice":"1637","localprice":"1637","currencyfactor":"1","calcshare":"1.40798483760886000","ca":null,"newcalcprice":1637,"newlocalprice":1637,"newcalcshare":"1.40798483760886000"},{"id":"5048","name":"Trend Micro Inc\/Japan","isin":"JP3637300009","ticker":"4704 JP Equity","curr":"JPY","divcurr":"JPY","sedol":"6125286","cusip":"","countryname":"Japan","calcprice":"3635","localprice":"3635","currencyfactor":"1","calcshare":"0.49199922150343600","ca":null,"newcalcprice":3635,"newlocalprice":3635,"newcalcshare":"0.49199922150343600"},{"id":"5049","name":"Doshisha Co Ltd","isin":"JP3638000004","ticker":"7483 JP Equity","curr":"JPY","divcurr":"JPY","sedol":"6235992","cusip":"","countryname":"Japan","calcprice":"1679","localprice":"1679","currencyfactor":"1","calcshare":"0.921522548857","ca":null,"newcalcprice":1679,"newlocalprice":1679,"newcalcshare":"0.921522548857"},{"id":"5050","name":"Doutor Nichires Holdings Co Ltd","isin":"JP3639100001","ticker":"3087 JP Equity","curr":"JPY","divcurr":"JPY","sedol":"B249GF3","cusip":"","countryname":"Japan","calcprice":"1692","localprice":"1692","currencyfactor":"1","calcshare":"0.98902739586721300","ca":null,"newcalcprice":1692,"newlocalprice":1692,"newcalcshare":"0.98902739586721300"},{"id":"5051","name":"Don Quijote Holdings Co Ltd","isin":"JP3639650005","ticker":"7532 JP Equity","curr":"JPY","divcurr":"JPY","sedol":"6269861","cusip":"","countryname":"Japan","calcprice":"8130","localprice":"8130","currencyfactor":"1","calcshare":"0.27866835905954600","ca":null,"newcalcprice":8130,"newlocalprice":8130,"newcalcshare":"0.27866835905954600"},{"id":"5052","name":"Nishimatsuya Chain Co Ltd","isin":"JP3659300002","ticker":"7545 JP Equity","curr":"JPY","divcurr":"JPY","sedol":"6016926","cusip":"","countryname":"Japan","calcprice":"1083","localprice":"1083","currencyfactor":"1","calcshare":"2.06850028993131000","ca":null,"newcalcprice":1083,"newlocalprice":1083,"newcalcshare":"2.06850028993131000"},{"id":"5053","name":"Nichii Gakkan Co","isin":"JP3660900006","ticker":"9792 JP Equity","curr":"JPY","divcurr":"JPY","sedol":"6622356","cusip":"","countryname":"Japan","calcprice":"904","localprice":"904","currencyfactor":"1","calcshare":"1.93950695336544000","ca":null,"newcalcprice":904,"newlocalprice":904,"newcalcshare":"1.93950695336544000"},{"id":"5054","name":"Nissei ASB Machine Co Ltd","isin":"JP3678200001","ticker":"6284 JP Equity","curr":"JPY","divcurr":"JPY","sedol":"6644974","cusip":"","countryname":"Japan","calcprice":"2851","localprice":"2851","currencyfactor":"1","calcshare":"0.82426750786661700","ca":null,"newcalcprice":2851,"newlocalprice":2851,"newcalcshare":"0.82426750786661700"},{"id":"5055","name":"Nihon Enterprise Co Ltd","isin":"JP3689470007","ticker":"4829 JP Equity","curr":"JPY","divcurr":"JPY","sedol":"6322452","cusip":"","countryname":"Japan","calcprice":"466","localprice":"466","currencyfactor":"1","calcshare":"3.66668893499403000","ca":null,"newcalcprice":466,"newlocalprice":466,"newcalcshare":"3.66668893499403000"},{"id":"5056","name":"JCR Pharmaceuticals Co Ltd","isin":"JP3701000006","ticker":"4552 JP Equity","curr":"JPY","divcurr":"JPY","sedol":"6467591","cusip":"","countryname":"Japan","calcprice":"2324","localprice":"2324","currencyfactor":"1","calcshare":"0.60706770446921000","ca":null,"newcalcprice":2324,"newlocalprice":2324,"newcalcshare":"0.60706770446921000"},{"id":"5057","name":"Nippon Parking Development Co Ltd","isin":"JP3728000005","ticker":"2353 JP Equity","curr":"JPY","divcurr":"JPY","sedol":"6583754","cusip":"","countryname":"Japan","calcprice":"122","localprice":"122","currencyfactor":"1","calcshare":"13.71399404820600000","ca":null,"newcalcprice":122,"newlocalprice":122,"newcalcshare":"13.71399404820600000"},{"id":"5058","name":"Japan Digital Laboratory Co Ltd","isin":"JP3732950005","ticker":"6935 JP Equity","curr":"JPY","divcurr":"JPY","sedol":"6468505","cusip":"","countryname":"Japan","calcprice":"1696","localprice":"1696","currencyfactor":"1","calcshare":"0.84138997300587600","ca":null,"newcalcprice":1696,"newlocalprice":1696,"newcalcshare":"0.84138997300587600"},{"id":"5059","name":"Nidec Corp","isin":"JP3734800000","ticker":"6594 JP Equity","curr":"JPY","divcurr":"JPY","sedol":"6640682","cusip":"","countryname":"Japan","calcprice":"8082","localprice":"8082","currencyfactor":"1","calcshare":"0.23558464008145000","ca":null,"newcalcprice":8082,"newlocalprice":8082,"newcalcshare":"0.23558464008145000"},{"id":"5060","name":"Nihon Trim Co Ltd","isin":"JP3739700007","ticker":"6788 JP Equity","curr":"JPY","divcurr":"JPY","sedol":"6305497","cusip":"","countryname":"Japan","calcprice":"2525","localprice":"2525","currencyfactor":"1","calcshare":"0.56547962471498800","ca":null,"newcalcprice":2525,"newlocalprice":2525,"newcalcshare":"0.56547962471498800"},{"id":"5061","name":"Relo Holdings Inc","isin":"JP3755200007","ticker":"8876 JP Equity","curr":"JPY","divcurr":"JPY","sedol":"6173906","cusip":"","countryname":"Japan","calcprice":"8310","localprice":"8310","currencyfactor":"1","calcshare":"0.22767022798982500","ca":null,"newcalcprice":8310,"newlocalprice":8310,"newcalcshare":"0.22767022798982500"},{"id":"5062","name":"Nitori Holdings Co Ltd","isin":"JP3756100008","ticker":"9843 JP Equity","curr":"JPY","divcurr":"JPY","sedol":"6644800","cusip":"","countryname":"Japan","calcprice":"6630","localprice":"6630","currencyfactor":"1","calcshare":"0.27471249907289600","ca":null,"newcalcprice":6630,"newlocalprice":6630,"newcalcshare":"0.27471249907289600"},{"id":"5063","name":"Nifco Inc\/Japan","isin":"JP3756200006","ticker":"7988 JP Equity","curr":"JPY","divcurr":"JPY","sedol":"6639163","cusip":"","countryname":"Japan","calcprice":"3995","localprice":"3995","currencyfactor":"1","calcshare":"0.49976391509961600","ca":null,"newcalcprice":3995,"newlocalprice":3995,"newcalcshare":"0.49976391509961600"},{"id":"5064","name":"Next Co Ltd","isin":"JP3758140002","ticker":"2120 JP Equity","curr":"JPY","divcurr":"JPY","sedol":"B1FM483","cusip":"","countryname":"Japan","calcprice":"978","localprice":"978","currencyfactor":"1","calcshare":"2.21869712627027000","ca":null,"newcalcprice":978,"newlocalprice":978,"newcalcshare":"2.21869712627027000"},{"id":"5065","name":"Netyear Group Corp","isin":"JP3758180008","ticker":"3622 JP Equity","curr":"JPY","divcurr":"JPY","sedol":"B2PFNM6","cusip":"","countryname":"Japan","calcprice":"1234","localprice":"1234","currencyfactor":"1","calcshare":"1.21795611477074000","ca":null,"newcalcprice":1234,"newlocalprice":1234,"newcalcshare":"1.21795611477074000"},{"id":"5066","name":"Hearts United Group Co Ltd","isin":"JP3765110006","ticker":"3676 JP Equity","curr":"JPY","divcurr":"JPY","sedol":"BDFLKD1","cusip":"","countryname":"Japan","calcprice":"1825","localprice":"1825","currencyfactor":"1","calcshare":"0.85418207166364000","ca":null,"newcalcprice":1825,"newlocalprice":1825,"newcalcshare":"0.85418207166364000"},{"id":"5067","name":"Piped Bits Co Ltd","isin":"JP3780500009","ticker":"3831 JP Equity","curr":"JPY","divcurr":"JPY","sedol":"B1HMJT7","cusip":"","countryname":"Japan","calcprice":"1674","localprice":"1674","currencyfactor":"1","calcshare":"1.05237295717351000","ca":null,"newcalcprice":1674,"newlocalprice":1674,"newcalcshare":"1.05237295717351000"},{"id":"5068","name":"Pal Co Ltd","isin":"JP3781650001","ticker":"2726 JP Equity","curr":"JPY","divcurr":"JPY","sedol":"6421898","cusip":"","countryname":"Japan","calcprice":"3115","localprice":"3115","currencyfactor":"1","calcshare":"0.57863031366184800","ca":null,"newcalcprice":3115,"newlocalprice":3115,"newcalcshare":"0.57863031366184800"},{"id":"5069","name":"BML Inc","isin":"JP3799700004","ticker":"4694 JP Equity","curr":"JPY","divcurr":"JPY","sedol":"6197876","cusip":"","countryname":"Japan","calcprice":"3370","localprice":"3370","currencyfactor":"1","calcshare":"0.49691219518464000","ca":null,"newcalcprice":3370,"newlocalprice":3370,"newcalcshare":"0.49691219518464000"},{"id":"5070","name":"Bit-isle Inc","isin":"JP3800380002","ticker":"3811 JP Equity","curr":"JPY","divcurr":"JPY","sedol":"B17FRM5","cusip":"","countryname":"Japan","calcprice":"457","localprice":"457","currencyfactor":"1","calcshare":"2.89796546442955000","ca":null,"newcalcprice":457,"newlocalprice":457,"newcalcshare":"2.89796546442955000"},{"id":"5071","name":"Bic Camera Inc","isin":"JP3800390001","ticker":"3048 JP Equity","curr":"JPY","divcurr":"JPY","sedol":"B194YN0","cusip":"","countryname":"Japan","calcprice":"1103","localprice":"1103","currencyfactor":"1","calcshare":"1.67630148616185000","ca":null,"newcalcprice":1103,"newlocalprice":1103,"newcalcshare":"1.67630148616185000"},{"id":"5072","name":"Fast Retailing Co Ltd","isin":"JP3802300008","ticker":"9983 JP Equity","curr":"JPY","divcurr":"JPY","sedol":"6332439","cusip":"","countryname":"Japan","calcprice":"43415","localprice":"43415","currencyfactor":"1","calcshare":"0.04724473739650520","ca":null,"newcalcprice":43415,"newlocalprice":43415,"newcalcshare":"0.04724473739650520"},{"id":"5073","name":"Fancl Corp","isin":"JP3802670004","ticker":"4921 JP Equity","curr":"JPY","divcurr":"JPY","sedol":"6131261","cusip":"","countryname":"Japan","calcprice":"1674","localprice":"1674","currencyfactor":"1","calcshare":"1.35328457196749000","ca":null,"newcalcprice":1674,"newlocalprice":1674,"newcalcshare":"1.35328457196749000"},{"id":"5074","name":"Fields Corp","isin":"JP3802680003","ticker":"2767 JP Equity","curr":"JPY","divcurr":"JPY","sedol":"6591478","cusip":"","countryname":"Japan","calcprice":"1523","localprice":"1523","currencyfactor":"1","calcshare":"1.08854827757635000","ca":null,"newcalcprice":1523,"newlocalprice":1523,"newcalcshare":"1.08854827757635000"},{"id":"5075","name":"Ferrotec Corp","isin":"JP3802720007","ticker":"6890 JP Equity","curr":"JPY","divcurr":"JPY","sedol":"6354273","cusip":"","countryname":"Japan","calcprice":"618","localprice":"618","currencyfactor":"1","calcshare":"2.60730126365593000","ca":null,"newcalcprice":618,"newlocalprice":618,"newcalcshare":"2.60730126365593000"},{"id":"5076","name":"F@N Communications Inc","isin":"JP3802840003","ticker":"2461 JP Equity","curr":"JPY","divcurr":"JPY","sedol":"B0N9WT6","cusip":"","countryname":"Japan","calcprice":"1357","localprice":"1357","currencyfactor":"1","calcshare":"1.36495081827756000","ca":null,"newcalcprice":1357,"newlocalprice":1357,"newcalcshare":"1.36495081827756000"},{"id":"5077","name":"Funai Electric Co Ltd","isin":"JP3825850005","ticker":"6839 JP Equity","curr":"JPY","divcurr":"JPY","sedol":"6141550","cusip":"","countryname":"Japan","calcprice":"1489","localprice":"1489","currencyfactor":"1","calcshare":"1.47599766451031000","ca":null,"newcalcprice":1489,"newlocalprice":1489,"newcalcshare":"1.47599766451031000"},{"id":"5078","name":"Freesia Macross Corp","isin":"JP3826600003","ticker":"6343 JP Equity","curr":"JPY","divcurr":"JPY","sedol":"6871705","cusip":"","countryname":"Japan","calcprice":"31","localprice":"31","currencyfactor":"1","calcshare":"62.20275871864870000","ca":null,"newcalcprice":31,"newlocalprice":31,"newcalcshare":"62.20275871864870000"},{"id":"5079","name":"Freebit Co Ltd","isin":"JP3826720009","ticker":"3843 JP Equity","curr":"JPY","divcurr":"JPY","sedol":"B1RMMJ8","cusip":"","countryname":"Japan","calcprice":"1278","localprice":"1278","currencyfactor":"1","calcshare":"1.17048201889930000","ca":null,"newcalcprice":1278,"newlocalprice":1278,"newcalcshare":"1.17048201889930000"},{"id":"5080","name":"FULLCAST Holdings Co Ltd","isin":"JP3827800008","ticker":"4848 JP Equity","curr":"JPY","divcurr":"JPY","sedol":"6352404","cusip":"","countryname":"Japan","calcprice":"480","localprice":"480","currencyfactor":"1","calcshare":"2.94700041306626000","ca":null,"newcalcprice":480,"newlocalprice":480,"newcalcshare":"2.94700041306626000"},{"id":"5081","name":"V Technology Co Ltd","isin":"JP3829900004","ticker":"7717 JP Equity","curr":"JPY","divcurr":"JPY","sedol":"6301989","cusip":"","countryname":"Japan","calcprice":"2435","localprice":"2435","currencyfactor":"1","calcshare":"0.56456312613360200","ca":null,"newcalcprice":2435,"newlocalprice":2435,"newcalcshare":"0.56456312613360200"},{"id":"5082","name":"Precision System Science Co Ltd","isin":"JP3833400009","ticker":"7707 JP Equity","curr":"JPY","divcurr":"JPY","sedol":"6318246","cusip":"","countryname":"Japan","calcprice":"1018","localprice":"1018","currencyfactor":"1","calcshare":"1.64619777327237000","ca":null,"newcalcprice":1018,"newlocalprice":1018,"newcalcshare":"1.64619777327237000"},{"id":"5083","name":"Plenus Co Ltd","isin":"JP3833700002","ticker":"9945 JP Equity","curr":"JPY","divcurr":"JPY","sedol":"6692702","cusip":"","countryname":"Japan","calcprice":"2082","localprice":"2082","currencyfactor":"1","calcshare":"0.67954633012959900","ca":null,"newcalcprice":2082,"newlocalprice":2082,"newcalcshare":"0.67954633012959900"},{"id":"5084","name":"Hogy Medical Co Ltd","isin":"JP3840800001","ticker":"3593 JP Equity","curr":"JPY","divcurr":"JPY","sedol":"6439040","cusip":"","countryname":"Japan","calcprice":"5820","localprice":"5820","currencyfactor":"1","calcshare":"0.30237452154898700","ca":null,"newcalcprice":5820,"newlocalprice":5820,"newcalcshare":"0.30237452154898700"},{"id":"5085","name":"Horiba Ltd","isin":"JP3853000002","ticker":"6856 JP Equity","curr":"JPY","divcurr":"JPY","sedol":"6437947","cusip":"","countryname":"Japan","calcprice":"4250","localprice":"4250","currencyfactor":"1","calcshare":"0.43379258882245600","ca":null,"newcalcprice":4250,"newlocalprice":4250,"newcalcshare":"0.43379258882245600"},{"id":"5086","name":"VT Holdings Co Ltd","isin":"JP3854700006","ticker":"7593 JP Equity","curr":"JPY","divcurr":"JPY","sedol":"6127334","cusip":"","countryname":"Japan","calcprice":"406","localprice":"406","currencyfactor":"1","calcshare":"4.18672414452443000","ca":null,"newcalcprice":406,"newlocalprice":406,"newcalcshare":"4.18672414452443000"},{"id":"5087","name":"Marvelous Inc","isin":"JP3860230006","ticker":"7844 JP Equity","curr":"JPY","divcurr":"JPY","sedol":"6558901","cusip":"","countryname":"Japan","calcprice":"1920","localprice":"1920","currencyfactor":"1","calcshare":"1.48607273389263000","ca":null,"newcalcprice":1920,"newlocalprice":1920,"newcalcshare":"1.48607273389263000"},{"id":"5088","name":"Macnica Inc","isin":"JP3862950007","ticker":"7631 JP Equity","curr":"JPY","divcurr":"JPY","sedol":"6207894","cusip":"","countryname":"Japan","calcprice":"3280","localprice":"3280","currencyfactor":"1","calcshare":"0.48379923447837900","ca":null,"newcalcprice":3280,"newlocalprice":3280,"newcalcshare":"0.48379923447837900"},{"id":"5089","name":"Monex Group Inc","isin":"JP3869970008","ticker":"8698 JP Equity","curr":"JPY","divcurr":"JPY","sedol":"B01S2L7","cusip":"","countryname":"Japan","calcprice":"304","localprice":"304","currencyfactor":"1","calcshare":"5.67321577889955000","ca":null,"newcalcprice":304,"newlocalprice":304,"newcalcshare":"5.67321577889955000"},{"id":"5090","name":"Mabuchi Motor Co Ltd","isin":"JP3870000001","ticker":"6592 JP Equity","curr":"JPY","divcurr":"JPY","sedol":"6551030","cusip":"","countryname":"Japan","calcprice":"10100","localprice":"10100","currencyfactor":"1","calcshare":"0.18029785135840200","ca":null,"newcalcprice":10100,"newlocalprice":10100,"newcalcshare":"0.18029785135840200"},{"id":"5091","name":"Mamezou Holdings Co Ltd","isin":"JP3870320003","ticker":"3756 JP Equity","curr":"JPY","divcurr":"JPY","sedol":"B034QH7","cusip":"","countryname":"Japan","calcprice":"666","localprice":"666","currencyfactor":"1","calcshare":"2.65904922766742000","ca":null,"newcalcprice":666,"newlocalprice":666,"newcalcshare":"2.65904922766742000"},{"id":"5092","name":"Message Co Ltd","isin":"JP3921020008","ticker":"2400 JP Equity","curr":"JPY","divcurr":"JPY","sedol":"B00HWZ9","cusip":"","countryname":"Japan","calcprice":"3255","localprice":"3255","currencyfactor":"1","calcshare":"0.45004579951477100","ca":null,"newcalcprice":3255,"newlocalprice":3255,"newcalcshare":"0.45004579951477100"},{"id":"5093","name":"Melco Holdings Inc","isin":"JP3921080002","ticker":"6676 JP Equity","curr":"JPY","divcurr":"JPY","sedol":"6688143","cusip":"","countryname":"Japan","calcprice":"1736","localprice":"1736","currencyfactor":"1","calcshare":"0.82937011624864900","ca":null,"newcalcprice":1736,"newlocalprice":1736,"newcalcshare":"0.82937011624864900"},{"id":"5094","name":"Asia Growth Capital Ltd","isin":"JP3926000005","ticker":"6993 JP Equity","curr":"JPY","divcurr":"JPY","sedol":"6602507","cusip":"","countryname":"Japan","calcprice":"156","localprice":"156","currencyfactor":"1","calcshare":"10.75109409951950000","ca":null,"newcalcprice":156,"newlocalprice":156,"newcalcshare":"10.75109409951950000"},{"id":"5095","name":"Yahoo Japan Corp","isin":"JP3933800009","ticker":"4689 JP Equity","curr":"JPY","divcurr":"JPY","sedol":"6084848","cusip":"","countryname":"Japan","calcprice":"426","localprice":"426","currencyfactor":"1","calcshare":"4.09806410381685000","ca":null,"newcalcprice":426,"newlocalprice":426,"newcalcshare":"4.09806410381685000"},{"id":"5096","name":"Yamada Denki Co Ltd","isin":"JP3939000000","ticker":"9831 JP Equity","curr":"JPY","divcurr":"JPY","sedol":"6985026","cusip":"","countryname":"Japan","calcprice":"389","localprice":"389","currencyfactor":"1","calcshare":"5.24601579554868000","ca":null,"newcalcprice":389,"newlocalprice":389,"newcalcshare":"5.24601579554868000"},{"id":"5097","name":"Ubic Inc","isin":"JP3944630007","ticker":"2158 JP Equity","curr":"JPY","divcurr":"JPY","sedol":"B1Y4DN8","cusip":"","countryname":"Japan","calcprice":"689","localprice":"689","currencyfactor":"1","calcshare":"2.09588116019514000","ca":null,"newcalcprice":689,"newlocalprice":689,"newcalcshare":"2.09588116019514000"},{"id":"5098","name":"United Arrows Ltd","isin":"JP3949400000","ticker":"7606 JP Equity","curr":"JPY","divcurr":"JPY","sedol":"6166597","cusip":"","countryname":"Japan","calcprice":"3065","localprice":"3065","currencyfactor":"1","calcshare":"0.42325084911838700","ca":null,"newcalcprice":3065,"newlocalprice":3065,"newcalcshare":"0.42325084911838700"},{"id":"5099","name":"UT Holdings Co Ltd","isin":"JP3949500007","ticker":"2146 JP Equity","curr":"JPY","divcurr":"JPY","sedol":"B1V04K3","cusip":"","countryname":"Japan","calcprice":"474","localprice":"474","currencyfactor":"1","calcshare":"2.97722605832848000","ca":null,"newcalcprice":474,"newlocalprice":474,"newcalcshare":"2.97722605832848000"},{"id":"5100","name":"Unicharm Corp","isin":"JP3951600000","ticker":"8113 JP Equity","curr":"JPY","divcurr":"JPY","sedol":"6911485","cusip":"","countryname":"Japan","calcprice":"2968","localprice":"2968","currencyfactor":"1","calcshare":"0.700970181428","ca":null,"newcalcprice":2968,"newlocalprice":2968,"newcalcshare":"0.700970181428"},{"id":"5101","name":"Uniden Corp","isin":"JP3952000002","ticker":"6815 JP Equity","curr":"JPY","divcurr":"JPY","sedol":"6911515","cusip":"","countryname":"Japan","calcprice":"235","localprice":"235","currencyfactor":"1","calcshare":"6.85699702410300000","ca":null,"newcalcprice":235,"newlocalprice":235,"newcalcshare":"6.85699702410300000"},{"id":"5102","name":"Yumeshin Holdings Co Ltd","isin":"JP3952850000","ticker":"2362 JP Equity","curr":"JPY","divcurr":"JPY","sedol":"6599546","cusip":"","countryname":"Japan","calcprice":"698","localprice":"698","currencyfactor":"1","calcshare":"1.94600809399124000","ca":null,"newcalcprice":698,"newlocalprice":698,"newcalcshare":"1.94600809399124000"},{"id":"5103","name":"Round One Corp","isin":"JP3966800009","ticker":"4680 JP Equity","curr":"JPY","divcurr":"JPY","sedol":"6248365","cusip":"","countryname":"Japan","calcprice":"727","localprice":"727","currencyfactor":"1","calcshare":"2.57263994700467000","ca":null,"newcalcprice":727,"newlocalprice":727,"newcalcshare":"2.57263994700467000"},{"id":"5104","name":"Resorttrust Inc","isin":"JP3974450003","ticker":"4681 JP Equity","curr":"JPY","divcurr":"JPY","sedol":"6044132","cusip":"","countryname":"Japan","calcprice":"2581","localprice":"2581","currencyfactor":"1","calcshare":"0.72358838559292200","ca":null,"newcalcprice":2581,"newlocalprice":2581,"newcalcshare":"0.72358838559292200"},{"id":"5105","name":"Link And Motivation Inc","isin":"JP3977020001","ticker":"2170 JP Equity","curr":"JPY","divcurr":"JPY","sedol":"B298ZY7","cusip":"","countryname":"Japan","calcprice":"165","localprice":"165","currencyfactor":"1","calcshare":"10.42920505462370000","ca":null,"newcalcprice":165,"newlocalprice":165,"newcalcshare":"10.42920505462370000"},{"id":"5106","name":"Raysum Co Ltd","isin":"JP3979100009","ticker":"8890 JP Equity","curr":"JPY","divcurr":"JPY","sedol":"6335892","cusip":"","countryname":"Japan","calcprice":"1140","localprice":"1140","currencyfactor":"1","calcshare":"1.73301218320613000","ca":null,"newcalcprice":1140,"newlocalprice":1140,"newcalcshare":"1.73301218320613000"},{"id":"5107","name":"Rohm Co Ltd","isin":"JP3982800009","ticker":"6963 JP Equity","curr":"JPY","divcurr":"JPY","sedol":"6747204","cusip":"","countryname":"Japan","calcprice":"7910","localprice":"7910","currencyfactor":"1","calcshare":"0.24496163771057100","ca":null,"newcalcprice":7910,"newlocalprice":7910,"newcalcshare":"0.24496163771057100"},{"id":"5108","name":"Wakita & Co Ltd","isin":"JP3992000004","ticker":"8125 JP Equity","curr":"JPY","divcurr":"JPY","sedol":"6933735","cusip":"","countryname":"Japan","calcprice":"1132","localprice":"1132","currencyfactor":"1","calcshare":"1.53587058564565000","ca":null,"newcalcprice":1132,"newlocalprice":1132,"newcalcshare":"1.53587058564565000"},{"id":"5109","name":"Advanced Media Inc\/Japan","isin":"JP3122150000","ticker":"3773 JP Equity","curr":"JPY","divcurr":"JPY","sedol":"B0994D8","cusip":"","countryname":"Japan","calcprice":"775","localprice":"775","currencyfactor":"1","calcshare":"1.81993442437008000","ca":null,"newcalcprice":775,"newlocalprice":775,"newcalcshare":"1.81993442437008000"},{"id":"5110","name":"Aplix IP Holdings Corp","isin":"JP3122610003","ticker":"3727 JP Equity","curr":"JPY","divcurr":"JPY","sedol":"6714587","cusip":"","countryname":"Japan","calcprice":"1204","localprice":"1204","currencyfactor":"1","calcshare":"1.11789296798598000","ca":null,"newcalcprice":1204,"newlocalprice":1204,"newcalcshare":"1.11789296798598000"},{"id":"5111","name":"Sosei Group Corp","isin":"JP3431300007","ticker":"4565 JP Equity","curr":"JPY","divcurr":"JPY","sedol":"B01QMC2","cusip":"","countryname":"Japan","calcprice":"4340","localprice":"4340","currencyfactor":"1","calcshare":"0.36134382658136200","ca":null,"newcalcprice":4340,"newlocalprice":4340,"newcalcshare":"0.36134382658136200"},{"id":"5112","name":"Drecom Co Ltd","isin":"JP3639570005","ticker":"3793 JP Equity","curr":"JPY","divcurr":"JPY","sedol":"B0WD3J6","cusip":"","countryname":"Japan","calcprice":"1752","localprice":"1752","currencyfactor":"1","calcshare":"0.94862594995760500","ca":null,"newcalcprice":1752,"newlocalprice":1752,"newcalcshare":"0.94862594995760500"},{"id":"5113","name":"Japan Communications Inc","isin":"JP3729600001","ticker":"9424 JP Equity","curr":"JPY","divcurr":"JPY","sedol":"B06NPS5","cusip":"","countryname":"Japan","calcprice":"576","localprice":"576","currencyfactor":"1","calcshare":"2.81824796783521000","ca":null,"newcalcprice":576,"newlocalprice":576,"newcalcshare":"2.81824796783521000"}]}}