{"152":{"id":"152","name":"Testing 36","code":"IT36I","investmentammount":"100000","divpvalue":"","indexvalue":"1000","divisor":"0","type":"1","cash_adjust":"1","curr":"USD","status":"1","dateAdded":"2014-12-24 04:17:18","lastupdated":"2014-12-26 02:24:45","dateStart":"2014-12-29","usersignoff":"1","dbusersignoff":"1","submitted":"1","finalsignoff":"1","runindex":"1","addtype":"1","zone":"2","calcdate":"0000-00-00","rebalance":"0","client_id":"4","display_currency":"1","ireturn":"1","ica":"0","recalc":"0","div_type":"1","currency_hedged":"0","priority":"0","client":"syntax","index_value":{"id":"7880","dateAdded":"2014-12-30 17:34:48","indxx_id":"152","code":"IT36I","market_value":"98706.598824","indxx_value":"988.08","date":"2014-12-30","olddivisor":"99.8975499637","newdivisor":"99.8975499637"},"values":[{"id":"24092","name":"Colgate-Palmolive Co.","isin":"US1941621039","ticker":"CL US Equity","curr":"USD","sedol":"","cusip":"","countryname":"United States","localprice":"70.04","currencyfactor":"1","calcprice":"70.04","calcshare":"28.16901408000000","ca":null},{"id":"24061","name":"Brunswick Corp.","isin":"US1170431092","ticker":"BC US Equity","curr":"USD","sedol":"","cusip":"","countryname":"United States","localprice":"51.61","currencyfactor":"1","calcprice":"51.61","calcshare":"39.73773098000000","ca":null},{"id":"24095","name":"ConocoPhillips","isin":"US20825C1045","ticker":"COP US Equity","curr":"USD","sedol":"","cusip":"","countryname":"United States","localprice":"69.93","currencyfactor":"1","calcprice":"69.93","calcshare":"28.14919071000000","ca":null},{"id":"24073","name":"Capital Southwest Corp.","isin":"US1405011073","ticker":"CSWC US Equity","curr":"USD","sedol":"","cusip":"","countryname":"United States","localprice":"37.95","currencyfactor":"1","calcprice":"37.95","calcshare":"50.06257822000000","ca":null},{"id":"24078","name":"Celanese Corp.","isin":"US1508701034","ticker":"CE US Equity","curr":"USD","sedol":"","cusip":"","countryname":"United States","localprice":"60.43","currencyfactor":"1","calcprice":"60.43","calcshare":"33.22811098000000","ca":null},{"id":"24093","name":"Colony Financial, Inc.","isin":"US19624R1068","ticker":"CLNY US Equity","curr":"USD","sedol":"","cusip":"","countryname":"United States","localprice":"24.03","currencyfactor":"1","calcprice":"24.03","calcshare":"81.86655751000000","ca":[{"identifier":"CLNY US Equity","action_id":"98929733","id":"90349","mnemonic":"ACQUIS","field_id":"1","company_name":"Colony Financial Inc","ann_date":"2014-11-19","eff_date":"2014-12-31","amd_date":"2014-11-19","currency":"N.A.","ca_values":[{"field_name":"CP_FLAG","field_value":"1","field_id":"1"},{"field_name":"CP_TKR","field_value":"249606Z US","field_id":"2"},{"field_name":"CP_NAME","field_value":"Cobalt Capital Partners LP","field_id":"3"},{"field_name":"CP_ID_BB_COMP","field_value":"8374850","field_id":"4"},{"field_name":"CP_UNIT","field_value":"Cobalt Capital Partners LP","field_id":"5"},{"field_name":"CP_TOT_AMT","field_value":"1600.000000","field_id":"6"},{"field_name":"CP_ACQUIS_TYP","field_value":"9","field_id":"7"},{"field_name":"CP_CASH","field_value":"0.000000","field_id":"8"},{"field_name":"CP_SH","field_value":"0.000000","field_id":"10"},{"field_name":"CP_DEBT","field_value":"0.000000","field_id":"12"},{"field_name":"CP_STAT","field_value":"1","field_id":"14"},{"field_name":"CP_DT_FLAG","field_value":"0","field_id":"15"},{"field_name":"CP_PCT_OWNED","field_value":"0.000000","field_id":"18"},{"field_name":"CP_PCT_SOUGHT","field_value":"100.000000","field_id":"19"},{"field_name":"CP_UNSOLICITED","field_value":"0","field_id":"20"},{"field_name":"CP_DETAIL_FLAG","field_value":"1","field_id":"21"},{"field_name":"CP_CRNCY","field_value":"USD","field_id":"22"},{"field_name":"CP_CASH_VAL","field_value":"0.000000","field_id":"23"},{"field_name":"CP_ARBITRAGE_PROF","field_value":"-999998.000000","field_id":"24"},{"field_name":"CP_ADVISORS_NUM","field_value":"1","field_id":"26"},{"field_name":"CP_SH_FRACTIONAL","field_value":"0","field_id":"27"},{"field_name":"CP_ADVISORS","field_value":";2;1;3;1;Acquirer Legal Adviser;1;Willkie Farr;13;100.000000;","field_id":"28"},{"field_name":"CP_ACQ_TKR","field_value":"CLNY US","field_id":"29"},{"field_name":"CP_ACQ_ID_BB_GLOBAL","field_value":"BBG000N7F029","field_id":"30"},{"field_name":"CP_ACQ_ID_BB_GLOBAL_COMPANY","field_value":"BBG001G7ZLK7","field_id":"31"},{"field_name":"CP_ACQ_ID_BB_SEC_NUM_DES","field_value":"CLNY","field_id":"32"},{"field_name":"CP_ACQ_FEED_SOURCE","field_value":"US","field_id":"33"},{"field_name":"CP_TARGET_TKR","field_value":"249606Z US","field_id":"34"},{"field_name":"CP_TARGET_ID_BB_GLOBAL","field_value":"BBG000BTF3L7","field_id":"35"},{"field_name":"CP_TARGET_ID_BB_GLOBAL_COMPANY","field_value":"BBG001G7B4H5","field_id":"36"},{"field_name":"CP_TARGET_ID_BB_SEC_NUM_DES","field_value":"249606Z","field_id":"37"},{"field_name":"CP_TARGET_FEED_SOURCE","field_value":"US","field_id":"38"}]}]},{"id":"24075","name":"The Carlyle Group LP","isin":"US14309L1026","ticker":"CG US Equity","curr":"USD","sedol":"","cusip":"","countryname":"United States","localprice":"27.34","currencyfactor":"1","calcprice":"27.34","calcshare":"73.28691829000000","ca":null},{"id":"24062","name":"Buckeye Partners LP","isin":"US1182301010","ticker":"BPL US Equity","curr":"USD","sedol":"","cusip":"","countryname":"United States","localprice":"76.65","currencyfactor":"1","calcprice":"76.65","calcshare":"25.93697316000000","ca":null},{"id":"24077","name":"Cedar Fair LP","isin":"US1501851067","ticker":"FUN US Equity","curr":"USD","sedol":"","cusip":"","countryname":"United States","localprice":"47.49","currencyfactor":"1","calcprice":"47.49","calcshare":"42.18519300000000","ca":null},{"id":"24070","name":"Cablevision Systems Corp.","isin":"US12686C1099","ticker":"CVC US Equity","curr":"USD","sedol":"","cusip":"","countryname":"United States","localprice":"21.08","currencyfactor":"1","calcprice":"21.08","calcshare":"97.89525208000000","ca":null},{"id":"24059","name":"Brady Corp.","isin":"US1046741062","ticker":"BRC US Equity","curr":"USD","sedol":"","cusip":"","countryname":"United States","localprice":"27.16","currencyfactor":"1","calcprice":"27.16","calcshare":"73.42143906000000","ca":null},{"id":"24069","name":"CA, Inc.","isin":"US12673P1057","ticker":"CA US Equity","curr":"USD","sedol":"","cusip":"","countryname":"United States","localprice":"30.79","currencyfactor":"1","calcprice":"30.79","calcshare":"63.83657836000000","ca":null},{"id":"24055","name":"The Blackstone Group LP","isin":"US09253U1088","ticker":"BX US Equity","curr":"USD","sedol":"","cusip":"","countryname":"United States","localprice":"33.95","currencyfactor":"1","calcprice":"33.95","calcshare":"58.89281508000000","ca":null},{"id":"24052","name":"Black Hills Corp.","isin":"US0921131092","ticker":"BKH US Equity","curr":"USD","sedol":"","cusip":"","countryname":"United States","localprice":"54.16","currencyfactor":"1","calcprice":"54.16","calcshare":"37.67897513000000","ca":null},{"id":"24066","name":"CVR Energy, Inc.","isin":"US12662P1084","ticker":"CVI US Equity","curr":"USD","sedol":"","cusip":"","countryname":"United States","localprice":"39.12","currencyfactor":"1","calcprice":"39.12","calcshare":"50.47955578000000","ca":null},{"id":"24089","name":"Coach, Inc.","isin":"US1897541041","ticker":"COH US Equity","curr":"USD","sedol":"","cusip":"","countryname":"United States","localprice":"37.86","currencyfactor":"1","calcprice":"37.86","calcshare":"53.76344086000000","ca":null},{"id":"24056","name":"H&R Block, Inc.","isin":"US0936711052","ticker":"HRB US Equity","curr":"USD","sedol":"","cusip":"","countryname":"United States","localprice":"33.66","currencyfactor":"1","calcprice":"33.66","calcshare":"59.17159763000000","ca":null},{"id":"24090","name":"The Coca-Cola Co.","isin":"US1912161007","ticker":"KO US Equity","curr":"USD","sedol":"","cusip":"","countryname":"United States","localprice":"42.76","currencyfactor":"1","calcprice":"42.76","calcshare":"46.54410054000000","ca":null},{"id":"24067","name":"CVR Refining LP","isin":"US12663P1075","ticker":"CVRR US Equity","curr":"USD","sedol":"","cusip":"","countryname":"United States","localprice":"16.82","currencyfactor":"1","calcprice":"16.82","calcshare":"116.89070720000000","ca":null},{"id":"24050","name":"Baxter International, Inc.","isin":"US0718131099","ticker":"BAX US Equity","curr":"USD","sedol":"","cusip":"","countryname":"United States","localprice":"74.02","currencyfactor":"1","calcprice":"74.02","calcshare":"26.84924151000000","ca":null},{"id":"24084","name":"Chimera Investment Corp.","isin":"US16934Q1094","ticker":"CIM US Equity","curr":"USD","sedol":"","cusip":"","countryname":"United States","localprice":"3.22","currencyfactor":"1","calcprice":"3.22","calcshare":"604.22960730000000","ca":null},{"id":"24074","name":"Capstead Mortgage Corp.","isin":"US14067E5069","ticker":"CMO US Equity","curr":"USD","sedol":"","cusip":"","countryname":"United States","localprice":"12.49","currencyfactor":"1","calcprice":"12.49","calcshare":"156.25000000000000","ca":null},{"id":"24081","name":"Chambers Street Properties","isin":"US1578421059","ticker":"CSG US Equity","curr":"USD","sedol":"","cusip":"","countryname":"United States","localprice":"8.23","currencyfactor":"1","calcprice":"8.23","calcshare":"245.39877300000000","ca":null},{"id":"24096","name":"Consolidated Edison, Inc.","isin":"US2091151041","ticker":"ED US Equity","curr":"USD","sedol":"","cusip":"","countryname":"United States","localprice":"66.91","currencyfactor":"1","calcprice":"66.91","calcshare":"30.29843963000000","ca":null},{"id":"24080","name":"CenturyLink, Inc.","isin":"US1567001060","ticker":"CTL US Equity","curr":"USD","sedol":"","cusip":"","countryname":"United States","localprice":"40.09","currencyfactor":"1","calcprice":"40.09","calcshare":"49.71414367000000","ca":null},{"id":"24083","name":"Chevron Corp.","isin":"US1667641005","ticker":"CVX US Equity","curr":"USD","sedol":"","cusip":"","countryname":"United States","localprice":"113.11","currencyfactor":"1","calcprice":"113.11","calcshare":"17.55155770000000","ca":null},{"id":"24088","name":"Civeo Corp.","isin":"US1787871078","ticker":"CVEO US Equity","curr":"USD","sedol":"","cusip":"","countryname":"United States","localprice":"3.92","currencyfactor":"1","calcprice":"3.92","calcshare":"233.37222870000000","ca":null},{"id":"24097","name":"CoreLogic, Inc.","isin":"US21871D1037","ticker":"CLGX US Equity","curr":"USD","sedol":"","cusip":"","countryname":"United States","localprice":"32.15","currencyfactor":"1","calcprice":"32.15","calcshare":"62.13109661000000","ca":null},{"id":"24065","name":"CST Brands, Inc.","isin":"US12646R1059","ticker":"CST US Equity","curr":"USD","sedol":"","cusip":"","countryname":"United States","localprice":"43.98","currencyfactor":"1","calcprice":"43.98","calcshare":"45.45454545000000","ca":null},{"id":"24076","name":"Caterpillar, Inc.","isin":"US1491231015","ticker":"CAT US Equity","curr":"USD","sedol":"","cusip":"","countryname":"United States","localprice":"92.59","currencyfactor":"1","calcprice":"92.59","calcshare":"21.39037433000000","ca":null},{"id":"24098","name":"Corning, Inc.","isin":"US2193501051","ticker":"GLW US Equity","curr":"USD","sedol":"","cusip":"","countryname":"United States","localprice":"23.19","currencyfactor":"1","calcprice":"23.19","calcshare":"86.43042351000000","ca":null},{"id":"24057","name":"BorgWarner, Inc.","isin":"US0997241064","ticker":"BWA US Equity","curr":"USD","sedol":"","cusip":"","countryname":"United States","localprice":"55.37","currencyfactor":"1","calcprice":"55.37","calcshare":"35.46728143000000","ca":null},{"id":"24091","name":"Coca-Cola Enterprises, Inc.","isin":"US19122T1097","ticker":"CCE US Equity","curr":"USD","sedol":"","cusip":"","countryname":"United States","localprice":"44.85","currencyfactor":"1","calcprice":"44.85","calcshare":"44.12089124000000","ca":null},{"id":"24094","name":"Comcast Corp.","isin":"US20030N1019","ticker":"CMCSA US Equity","curr":"USD","sedol":"","cusip":"","countryname":"United States","localprice":"58.87","currencyfactor":"1","calcprice":"58.87","calcshare":"34.54231434000000","ca":null},{"id":"24068","name":"CVS Health Corp.","isin":"US1266501006","ticker":"CVS US Equity","curr":"USD","sedol":"","cusip":"","countryname":"United States","localprice":"97.53","currencyfactor":"1","calcprice":"97.53","calcshare":"20.43527128000000","ca":null},{"id":"24053","name":"BlackRock, Inc.","isin":"US09247X1019","ticker":"BLK US Equity","curr":"USD","sedol":"","cusip":"","countryname":"United States","localprice":"362.08","currencyfactor":"1","calcprice":"362.08","calcshare":"5.49133741500000","ca":null},{"id":"24099","name":"Costco Wholesale Corp.","isin":"US22160K1051","ticker":"COST US Equity","curr":"USD","sedol":"","cusip":"","countryname":"United States","localprice":"143.49","currencyfactor":"1","calcprice":"143.49","calcshare":"13.87443635000000","ca":null},{"id":"24072","name":"Capital One Financial Corp.","isin":"US14040H1059","ticker":"COF US Equity","curr":"USD","sedol":"","cusip":"","countryname":"United States","localprice":"83.31","currencyfactor":"1","calcprice":"83.31","calcshare":"24.01536984000000","ca":null},{"id":"24060","name":"Brown-Forman Corp.","isin":"US1156372096","ticker":"BF\/B US Equity","curr":"USD","sedol":"","cusip":"","countryname":"United States","localprice":"88.75","currencyfactor":"1","calcprice":"88.75","calcshare":"22.21975336000000","ca":null},{"id":"24054","name":"BlackRock Kelso Capital Corp.","isin":"US0925331086","ticker":"BKCC US Equity","curr":"USD","sedol":"","cusip":"","countryname":"United States","localprice":"8.25","currencyfactor":"1","calcprice":"8.25","calcshare":"245.39877300000000","ca":null},{"id":"24082","name":"Cheniere Energy Partners LP","isin":"US16411Q1013","ticker":"CQP US Equity","curr":"USD","sedol":"","cusip":"","countryname":"United States","localprice":"31.03","currencyfactor":"1","calcprice":"31.03","calcshare":"65.87615283000000","ca":null},{"id":"24058","name":"Boston Properties, Inc.","isin":"US1011211018","ticker":"BXP US Equity","curr":"USD","sedol":"","cusip":"","countryname":"United States","localprice":"131.02","currencyfactor":"1","calcprice":"131.02","calcshare":"15.1806031695435","ca":null},{"id":"24051","name":"Becton, Dickinson & Co.","isin":"US0758871091","ticker":"BDX US Equity","curr":"USD","sedol":"","cusip":"","countryname":"United States","localprice":"139.93","currencyfactor":"1","calcprice":"139.93","calcshare":"14.44460494000000","ca":null},{"id":"24079","name":"CenterPoint Energy, Inc.","isin":"US15189T1079","ticker":"CNP US Equity","curr":"USD","sedol":"","cusip":"","countryname":"United States","localprice":"23.82","currencyfactor":"1","calcprice":"23.82","calcshare":"85.28784648000000","ca":null},{"id":"24071","name":"Campbell Soup Co.","isin":"US1344291091","ticker":"CPB US Equity","curr":"USD","sedol":"","cusip":"","countryname":"United States","localprice":"44.59","currencyfactor":"1","calcprice":"44.59","calcshare":"44.82294935000000","ca":null},{"id":"24064","name":"CMS Energy Corp.","isin":"US1258961002","ticker":"CMS US Equity","curr":"USD","sedol":"","cusip":"","countryname":"United States","localprice":"35.25","currencyfactor":"1","calcprice":"35.25","calcshare":"57.33944954000000","ca":null},{"id":"24087","name":"Cintas Corp.","isin":"US1729081059","ticker":"CTAS US Equity","curr":"USD","sedol":"","cusip":"","countryname":"United States","localprice":"79.02","currencyfactor":"1","calcprice":"79.02","calcshare":"25.11300854000000","ca":null},{"id":"24086","name":"Cincinnati Financial Corp.","isin":"US1720621010","ticker":"CINF US Equity","curr":"USD","sedol":"","cusip":"","countryname":"United States","localprice":"52.44","currencyfactor":"1","calcprice":"52.44","calcshare":"38.18980332000000","ca":null},{"id":"24085","name":"Church & Dwight Co., Inc.","isin":"US1713401024","ticker":"CHD US Equity","curr":"USD","sedol":"","cusip":"","countryname":"United States","localprice":"79.64","currencyfactor":"1","calcprice":"79.64","calcshare":"24.83546504000000","ca":null},{"id":"24063","name":"CBS Corp.","isin":"US1248572026","ticker":"CBS US Equity","curr":"USD","sedol":"","cusip":"","countryname":"United States","localprice":"55.83","currencyfactor":"1","calcprice":"55.83","calcshare":"35.82303421000000","ca":null}]}}